tasmota_metrics/__init__.py
tasmota_metrics/__main__.py
tasmota_metrics/core.py
tasmota_metrics/chip_info/esp32.yaml
tasmota_metrics/chip_info/esp32c2.yaml
tasmota_metrics/chip_info/esp32c3.yaml
tasmota_metrics/chip_info/esp32c6.yaml
tasmota_metrics/chip_info/esp32h2.yaml
tasmota_metrics/chip_info/esp32h4.yaml
tasmota_metrics/chip_info/esp32p4.yaml
tasmota_metrics/chip_info/esp32s2.yaml
tasmota_metrics/chip_info/esp32s3.yaml
tasmota_metrics-0.4.3.dist-info/LICENSE
tasmota_metrics-0.4.3.dist-info/METADATA
tasmota_metrics-0.4.3.dist-info/WHEEL
tasmota_metrics-0.4.3.dist-info/top_level.txt
tasmota_metrics-0.4.3.dist-info/RECORD
