Metadata-Version: 2.1
Name: tasmota-metrics
Version: 0.4.3
Summary: Firmware size analysis for ESP-IDF
Home-page: https://github.com/jason2866/tasmota-metrics
Author: Espressif Systems
Author-email: 
Keywords: espressif,embedded,project,size
Classifier: Development Status :: 4 - Beta
Classifier: Intended Audience :: Developers
Classifier: Natural Language :: English
Classifier: Environment :: Console
Classifier: Topic :: Software Development :: Embedded Systems
Classifier: License :: OSI Approved :: Apache Software License
Classifier: Programming Language :: Python :: 3.7
Classifier: Programming Language :: Python :: 3.8
Classifier: Programming Language :: Python :: 3.9
Classifier: Programming Language :: Python :: 3.10
Classifier: Programming Language :: Python :: 3.11
Classifier: Operating System :: POSIX
Classifier: Operating System :: Microsoft :: Windows
Classifier: Operating System :: MacOS :: MacOS X
Requires-Python: >=3.7
License-File: LICENSE
Requires-Dist: pyyaml
Provides-Extra: dev
Requires-Dist: pre-commit ; extra == 'dev'
Requires-Dist: coverage ; extra == 'dev'
Requires-Dist: jsonschema ; extra == 'dev'
